inkcut/__init__.py
inkcut/__main__.py
inkcut/app.py
inkcut/cli/__init__.py
inkcut/cli/extensions.py
inkcut/cli/manifest.enaml
inkcut/cli/plugin.py
inkcut/console/__init__.py
inkcut/console/manifest.enaml
inkcut/console/plugin.py
inkcut/console/view.enaml
inkcut/core/__init__.py
inkcut/core/api.py
inkcut/core/declarative.py
inkcut/core/manifest.enaml
inkcut/core/models.py
inkcut/core/plugin.py
inkcut/core/svg.py
inkcut/core/utils.py
inkcut/core/widgets.py
inkcut/core/workbench.py
inkcut/device/__init__.py
inkcut/device/dialogs.enaml
inkcut/device/extensions.py
inkcut/device/manifest.enaml
inkcut/device/plugin.py
inkcut/device/view.enaml
inkcut/device/contour/__init__.py
inkcut/device/contour/manifest.enaml
inkcut/device/contour/plugin.py
inkcut/device/contour/view.enaml
inkcut/device/drivers/__init__.py
inkcut/device/drivers/manifest.enaml
inkcut/device/filters/__init__.py
inkcut/device/filters/blade_offset.py
inkcut/device/filters/manifest.enaml
inkcut/device/filters/min_line.py
inkcut/device/filters/overcut.py
inkcut/device/filters/repeat.py
inkcut/device/filters/view.enaml
inkcut/device/pi/__init__.py
inkcut/device/pi/driver.py
inkcut/device/pi/manifest.enaml
inkcut/device/pi/view.enaml
inkcut/device/protocols/__init__.py
inkcut/device/protocols/camm.py
inkcut/device/protocols/debug.py
inkcut/device/protocols/dmpl.py
inkcut/device/protocols/gcode.py
inkcut/device/protocols/gpgl.py
inkcut/device/protocols/hpgl.py
inkcut/device/protocols/manifest.enaml
inkcut/device/protocols/view.enaml
inkcut/device/transports/__init__.py
inkcut/device/transports/disk/__init__.py
inkcut/device/transports/disk/manifest.enaml
inkcut/device/transports/disk/plugin.py
inkcut/device/transports/disk/settings.enaml
inkcut/device/transports/parallelport/__init__.py
inkcut/device/transports/parallelport/manifest.enaml
inkcut/device/transports/parallelport/plugin.py
inkcut/device/transports/parallelport/settings.enaml
inkcut/device/transports/printer/__init__.py
inkcut-2.1.7.dist-info/licenses/LICENSE
inkcut-2.1.7.dist-info/METADATA
inkcut-2.1.7.dist-info/WHEEL
inkcut-2.1.7.dist-info/entry_points.txt
inkcut-2.1.7.dist-info/top_level.txt
inkcut-2.1.7.dist-info/RECORD
