Metadata-Version: 2.4
Name: inkcut
Version: 2.1.7
Summary: An application for controlling 2D plotters, cutters, engravers, and CNC machines.
Home-page: https://github.com/codelv/inkcut/
Author: Inkcut team
Author-email: frmdstryr@gmail.com
License: GPLv3
License-File: LICENSE
Requires-Dist: twisted
Requires-Dist: enamlx>=0.4.2
Requires-Dist: pyqtgraph
Requires-Dist: qtconsole
Requires-Dist: pyserial>=3.5
Requires-Dist: jsonpickle
Requires-Dist: lxml
Requires-Dist: qt-reactor
Requires-Dist: faulthandler; python_version < "3.0"
Requires-Dist: enaml==0.10; python_version < "3.0"
Requires-Dist: enaml>=0.10; python_version > "3.0"
Requires-Dist: pycups; sys_platform == "linux2"
Requires-Dist: pycups; sys_platform == "linux"
Requires-Dist: pywin32; sys_platform == "win32"
Dynamic: author
Dynamic: author-email
Dynamic: description
Dynamic: description-content-type
Dynamic: home-page
Dynamic: license
Dynamic: license-file
Dynamic: requires-dist
Dynamic: summary
